nbsphinx_link/__init__.py
nbsphinx_link/_version.py
nbsphinx_link-1.3.0.dist-info/LICENSE
nbsphinx_link-1.3.0.dist-info/METADATA
nbsphinx_link-1.3.0.dist-info/WHEEL
nbsphinx_link-1.3.0.dist-info/top_level.txt
nbsphinx_link-1.3.0.dist-info/RECORD
