Metadata-Version: 1.1
Name: nbsphinx-link
Version: 1.3.0
Summary: A sphinx extension for including notebook files outside sphinx source root
Home-page: https://github.com/vidartf/nbsphinx-link
Author: Vidar Tonaas Fauske
Author-email: vidartf@gmail.com
License: BSD-3
Keywords: Interactive,Interpreter,Shell,Web
Platform: Linux
Platform: Mac OS X
Platform: Windows
Classifier: Intended Audience :: Developers
Classifier: License :: OSI Approved :: BSD License
Classifier: Programming Language :: Python
Classifier: Programming Language :: Python :: 2.7
Classifier: Programming Language :: Python :: 3
Classifier: Programming Language :: Python :: 3.4
Classifier: Programming Language :: Python :: 3.5
Classifier: Programming Language :: Python :: 3.6
